{
    "database": {
        "dataDirectory": "$HOME/db-data",
        "installDirectory": "$HOME/sonicbase",
        "copmressRecords": false,
        "useUnsafe": true,
        "maxJavaHeap": "10%",
        "maxJavaHeapTrigger": "20%",
        "user": "ubuntu",
        "maxProcessMemoryTrigger": "90%",
        "replicationFactor": 1,
        "shards" : [
          {
            "replicas": [
              {
                "publicAddress": "localhost",
                "privateAddress": "localhost",
                "port": 9010
              }
            ]
          }
        ],
      "clients": [
        {
          "publicAddress": "localhost",
          "privateAddress": "localhost",
          "port": 8080
        }
      ]
    }
}
